syncraft/__init__.py
syncraft/algebra.py
syncraft/analysis.py
syncraft/ast.py
syncraft/cache.py
syncraft/charset.py
syncraft/constraint.py
syncraft/dev.py
syncraft/fa.py
syncraft/finder.py
syncraft/generator.py
syncraft/input.py
syncraft/lexer.py
syncraft/parser.py
syncraft/path.py
syncraft/py.typed
syncraft/regex.py
syncraft/sqlite3.py
syncraft/syntax.py
syncraft/token.py
syncraft/utils.py
syncraft/cache/0323a09e1e0c6b6e2e03927451b2c035d6eb181fa866a4b162101715ffcc9362.lex
syncraft/cache/0ad89ff788cd0fc733b414415e4b1fd310460a9040541adc766062c7f861699e.lex
syncraft/cache/0ca268f038e813af17052b8ab051ae43e4057353caa1dea58effce47d33566d7.lex
syncraft/cache/0ca4b3915f90a20b730dfbbf73862b99c1b62849412412128b3ef604a71f937e.lex
syncraft/cache/139d2e8ffdf6c96c8d5c3f9508e0d27899d06cd396add66d4909f18495e42a1d.lex
syncraft/cache/25a112229cad318466527a053645784cfe36e9241eaeea856f4ce81adbfafc4c.lex
syncraft/cache/2bb80cb55dbf5d9902d2d31dbaa8c71ba9490fb5a190ccfbb688683039083b49.lex
syncraft/cache/2f47f5ba4a43cbc4db0afc870d719211a799f8fba03698984477484f7b6f965d.lex
syncraft/cache/30677f1ce02f17dd4e0d97213897801b44a50ff658933fb9efbf52dbe6a2a11c.lex
syncraft/cache/38266a113e15c92ecc48d4abf750a1a0b252070eb264ab71e1f19012d7528c7e.lex
syncraft/cache/390d35713387fe8508cf75bf55faf1b687b2bbaca5b72f36889a6768d0987f32.lex
syncraft/cache/3b1b656d9c899f56a20e81793d1d87ba38458257d08bb37a504d0c5f1987a24e.lex
syncraft/cache/3c4016322323afa5cfdfc2479f51da05d03d024c76dfce12022da54cf2540f37.lex
syncraft/cache/427810660487e85706307e9e5549fc85b4c23cda5a3406b6b0669ae54cbdae65.lex
syncraft/cache/49b33ff6f555bd8e97483b6ff3266b07c525184fb8f69363aacf81cb56fbf74b.lex
syncraft/cache/4e2c4a34b56daff8a0927135b5982478e357d507e0a332753da73693ac8799e5.lex
syncraft/cache/50aa0399e3d1a158b4d80daef829d30e5272dc588bd0c32941390f06241240f4.lex
syncraft/cache/5b8aff732507a9fb7a9dfc7a658b32fff905d523d2e1b6c575939f2c13184d02.lex
syncraft/cache/5deb7c7d3a82a6a19f1491eb9f3eb66e5170fd55f1211efa9a6fc71b19e1e9e8.lex
syncraft-0.3.2.dist-info/licenses/LICENSE
syncraft-0.3.2.dist-info/METADATA
syncraft-0.3.2.dist-info/WHEEL
syncraft-0.3.2.dist-info/top_level.txt
syncraft-0.3.2.dist-info/RECORD
