Metadata-Version: 2.4
Name: syncraft
Version: 0.3.2
Summary: Parser combinator library
Author-email: Michael Afmokt <michael@esacca.com>
License-Expression: MIT
Keywords: parser,combinator,sql,sqlite,generator,printer
Requires-Python: >=3.10
License-File: LICENSE
Requires-Dist: rstr>=3.2.2
Requires-Dist: sqlglot>=27.14.0
Dynamic: license-file
